{"exact_hash_to_version": [{"timestamp": "2021-02-11 06:33:04", "name": "channel-rust-1.50.0.toml", "url": "https://static.rust-lang.org/dist/channel-rust-1.50.0.toml", "commit_hash": "cb75ad5db02783e8b0222fee363c5f63f7e2cf5b", "rust_version": "1.50.0"}, {"timestamp": "2021-02-11 06:33:04", "name": "channel-rust-1.50.toml", "url": "https://static.rust-lang.org/dist/channel-rust-1.50.toml", "commit_hash": "cb75ad5db02783e8b0222fee363c5f63f7e2cf5b", "rust_version": "1.50"}, {"timestamp": "2021-03-25 07:11:35", "name": "channel-rust-1.51.0.toml", "url": "https://static.rust-lang.org/dist/channel-rust-1.51.0.toml", "commit_hash": "2fd73fabe469357a12c2c974c140f67e7cdd76d0", "rust_version": "1.51.0"}, {"timestamp": "2021-03-25 07:11:35", "name": "channel-rust-1.51.toml", "url": "https://static.rust-lang.org/dist/channel-rust-1.51.toml", "commit_hash": "2fd73fabe469357a12c2c974c140f67e7cdd76d0", "rust_version": "1.51"}, {"timestamp": "2021-05-06 08:50:01", "name": "channel-rust-1.52.0.toml", "url": "https://static.rust-lang.org/dist/channel-rust-1.52.0.toml", "commit_hash": "88f19c6dab716c6281af7602e30f413e809c5974", "rust_version": "1.52.0"}, {"timestamp": "2021-05-10 07:35:00", "name": "channel-rust-1.52.1.toml", "url": "https://static.rust-lang.org/dist/channel-rust-1.52.1.toml", "commit_hash": "9bc8c42bb2f19e745a63f3445f1ac248fb015e53", "rust_version": "1.52.1"}, {"timestamp": "2021-05-10 07:35:00", "name": "channel-rust-1.52.toml", "url": "https://static.rust-lang.org/dist/channel-rust-1.52.toml", "commit_hash": "9bc8c42bb2f19e745a63f3445f1ac248fb015e53", "rust_version": "1.52"}, {"timestamp": "2021-06-17 07:36:22", "name": "channel-rust-1.53.0.toml", "url": "https://static.rust-lang.org/dist/channel-rust-1.53.0.toml", "commit_hash": "53cb7b09b00cbea8754ffb78e7e3cb521cb8af4b", "rust_version": "1.53.0"}, {"timestamp": "2021-06-17 07:36:22", "name": "channel-rust-1.53.toml", "url": "https://static.rust-lang.org/dist/channel-rust-1.53.toml", "commit_hash": "53cb7b09b00cbea8754ffb78e7e3cb521cb8af4b", "rust_version": "1.53"}, {"timestamp": "2021-07-29 07:11:38", "name": "channel-rust-1.54.0.toml", "url": "https://static.rust-lang.org/dist/channel-rust-1.54.0.toml", "commit_hash": "a178d0322ce20e33eac124758e837cbd80a6f633", "rust_version": "1.54.0"}, {"timestamp": "2021-07-29 07:11:38", "name": "channel-rust-1.54.toml", "url": "https://static.rust-lang.org/dist/channel-rust-1.54.toml", "commit_hash": "a178d0322ce20e33eac124758e837cbd80a6f633", "rust_version": "1.54"}, {"timestamp": "2021-09-09 07:13:03", "name": "channel-rust-1.55.0.toml", "url": "https://static.rust-lang.org/dist/channel-rust-1.55.0.toml", "commit_hash": "c8dfcfe046a7680554bf4eb612bad840e7631c4b", "rust_version": "1.55.0"}, {"timestamp": "2021-09-09 07:13:03", "name": "channel-rust-1.55.toml", "url": "https://static.rust-lang.org/dist/channel-rust-1.55.toml", "commit_hash": "c8dfcfe046a7680554bf4eb612bad840e7631c4b", "rust_version": "1.55"}, {"timestamp": "2021-10-21 07:52:20", "name": "channel-rust-1.56.0.toml", "url": "https://static.rust-lang.org/dist/channel-rust-1.56.0.toml", "commit_hash": "09c42c45858d5f3aedfa670698275303a3d19afa", "rust_version": "1.56.0"}, {"timestamp": "2021-11-01 04:54:05", "name": "channel-rust-1.56.1.toml", "url": "https://static.rust-lang.org/dist/channel-rust-1.56.1.toml", "commit_hash": "59eed8a2aac0230a8b53e89d4e99d55912ba6b35", "rust_version": "1.56.1"}, {"timestamp": "2021-11-01 04:54:05", "name": "channel-rust-1.56.toml", "url": "https://static.rust-lang.org/dist/channel-rust-1.56.toml", "commit_hash": "59eed8a2aac0230a8b53e89d4e99d55912ba6b35", "rust_version": "1.56"}, {"timestamp": "2021-12-02 06:51:55", "name": "channel-rust-1.57.0.toml", "url": "https://static.rust-lang.org/dist/channel-rust-1.57.0.toml", "commit_hash": "f1edd0429582dd29cccacaf50fd134b05593bd9c", "rust_version": "1.57.0"}, {"timestamp": "2021-12-02 06:51:55", "name": "channel-rust-1.57.toml", "url": "https://static.rust-lang.org/dist/channel-rust-1.57.toml", "commit_hash": "f1edd0429582dd29cccacaf50fd134b05593bd9c", "rust_version": "1.57"}, {"timestamp": "2022-01-13 09:04:54", "name": "channel-rust-1.58.0.toml", "url": "https://static.rust-lang.org/dist/channel-rust-1.58.0.toml", "commit_hash": "02072b482a8b5357f7fb5e5637444ae30e423c40", "rust_version": "1.58.0"}, {"timestamp": "2022-01-20 13:41:15", "name": "channel-rust-1.58.1.toml", "url": "https://static.rust-lang.org/dist/channel-rust-1.58.1.toml", "commit_hash": "db9d1b20bba1968c1ec1fc49616d4742c1725b4b", "rust_version": "1.58.1"}, {"timestamp": "2022-01-20 13:41:15", "name": "channel-rust-1.58.toml", "url": "https://static.rust-lang.org/dist/channel-rust-1.58.toml", "commit_hash": "db9d1b20bba1968c1ec1fc49616d4742c1725b4b", "rust_version": "1.58"}, {"timestamp": "2022-02-24 08:55:22", "name": "channel-rust-1.59.0.toml", "url": "https://static.rust-lang.org/dist/channel-rust-1.59.0.toml", "commit_hash": "9d1b2106e23b1abd32fce1f17267604a5102f57a", "rust_version": "1.59.0"}, {"timestamp": "2022-02-24 08:55:22", "name": "channel-rust-1.59.toml", "url": "https://static.rust-lang.org/dist/channel-rust-1.59.toml", "commit_hash": "9d1b2106e23b1abd32fce1f17267604a5102f57a", "rust_version": "1.59"}, {"timestamp": "2022-04-07 06:55:45", "name": "channel-rust-1.60.0.toml", "url": "https://static.rust-lang.org/dist/channel-rust-1.60.0.toml", "commit_hash": "7737e0b5c4103216d6fd8cf941b7ab9bdbaace7c", "rust_version": "1.60.0"}, {"timestamp": "2022-04-07 06:55:45", "name": "channel-rust-1.60.toml", "url": "https://static.rust-lang.org/dist/channel-rust-1.60.toml", "commit_hash": "7737e0b5c4103216d6fd8cf941b7ab9bdbaace7c", "rust_version": "1.60"}, {"timestamp": "2022-05-19 07:01:01", "name": "channel-rust-1.61.0.toml", "url": "https://static.rust-lang.org/dist/channel-rust-1.61.0.toml", "commit_hash": "fe5b13d681f25ee6474be29d748c65adcd91f69e", "rust_version": "1.61.0"}, {"timestamp": "2022-05-19 07:01:01", "name": "channel-rust-1.61.toml", "url": "https://static.rust-lang.org/dist/channel-rust-1.61.toml", "commit_hash": "fe5b13d681f25ee6474be29d748c65adcd91f69e", "rust_version": "1.61"}, {"timestamp": "2022-06-30 09:28:33", "name": "channel-rust-1.62.0.toml", "url": "https://static.rust-lang.org/dist/channel-rust-1.62.0.toml", "commit_hash": "a8314ef7d0ec7b75c336af2c9857bfaf43002bfc", "rust_version": "1.62.0"}, {"timestamp": "2022-07-19 06:31:03", "name": "channel-rust-1.62.1.toml", "url": "https://static.rust-lang.org/dist/channel-rust-1.62.1.toml", "commit_hash": "e092d0b6b43f2de967af0887873151bb1c0b18d3", "rust_version": "1.62.1"}, {"timestamp": "2022-07-19 06:31:03", "name": "channel-rust-1.62.toml", "url": "https://static.rust-lang.org/dist/channel-rust-1.62.toml", "commit_hash": "e092d0b6b43f2de967af0887873151bb1c0b18d3", "rust_version": "1.62"}, {"timestamp": "2022-08-11 07:42:22", "name": "channel-rust-1.63.0.toml", "url": "https://static.rust-lang.org/dist/channel-rust-1.63.0.toml", "commit_hash": "4b91a6ea7258a947e59c6522cd5898e7c0a6a88f", "rust_version": "1.63.0"}, {"timestamp": "2022-08-11 07:42:22", "name": "channel-rust-1.63.toml", "url": "https://static.rust-lang.org/dist/channel-rust-1.63.toml", "commit_hash": "4b91a6ea7258a947e59c6522cd5898e7c0a6a88f", "rust_version": "1.63"}, {"timestamp": "2022-09-22 06:26:37", "name": "channel-rust-1.64.0.toml", "url": "https://static.rust-lang.org/dist/channel-rust-1.64.0.toml", "commit_hash": "a55dd71d5fb0ec5a6a3a9e8c27b2127ba491ce52", "rust_version": "1.64.0"}, {"timestamp": "2022-09-22 06:26:37", "name": "channel-rust-1.64.toml", "url": "https://static.rust-lang.org/dist/channel-rust-1.64.toml", "commit_hash": "a55dd71d5fb0ec5a6a3a9e8c27b2127ba491ce52", "rust_version": "1.64"}, {"timestamp": "2022-11-03 07:03:33", "name": "channel-rust-1.65.0.toml", "url": "https://static.rust-lang.org/dist/channel-rust-1.65.0.toml", "commit_hash": "897e37553bba8b42751c67658967889d11ecd120", "rust_version": "1.65.0"}, {"timestamp": "2022-11-03 07:03:33", "name": "channel-rust-1.65.toml", "url": "https://static.rust-lang.org/dist/channel-rust-1.65.toml", "commit_hash": "897e37553bba8b42751c67658967889d11ecd120", "rust_version": "1.65"}, {"timestamp": "2022-12-15 08:06:03", "name": "channel-rust-1.66.0.toml", "url": "https://static.rust-lang.org/dist/channel-rust-1.66.0.toml", "commit_hash": "69f9c33d71c871fc16ac445211281c6e7a340943", "rust_version": "1.66.0"}, {"timestamp": "2023-01-10 15:48:53", "name": "channel-rust-1.66.1.toml", "url": "https://static.rust-lang.org/dist/channel-rust-1.66.1.toml", "commit_hash": "90743e7298aca107ddaa0c202a4d3604e29bfeb6", "rust_version": "1.66.1"}, {"timestamp": "2023-01-10 15:48:53", "name": "channel-rust-1.66.toml", "url": "https://static.rust-lang.org/dist/channel-rust-1.66.toml", "commit_hash": "90743e7298aca107ddaa0c202a4d3604e29bfeb6", "rust_version": "1.66"}, {"timestamp": "2023-01-26 07:08:56", "name": "channel-rust-1.67.0.toml", "url": "https://static.rust-lang.org/dist/channel-rust-1.67.0.toml", "commit_hash": "fc594f15669680fa70d255faec3ca3fb507c3405", "rust_version": "1.67.0"}, {"timestamp": "2023-02-09 07:27:05", "name": "channel-rust-1.67.1.toml", "url": "https://static.rust-lang.org/dist/channel-rust-1.67.1.toml", "commit_hash": "d5a82bbd26e1ad8b7401f6a718a9c57c96905483", "rust_version": "1.67.1"}, {"timestamp": "2023-02-09 07:27:05", "name": "channel-rust-1.67.toml", "url": "https://static.rust-lang.org/dist/channel-rust-1.67.toml", "commit_hash": "d5a82bbd26e1ad8b7401f6a718a9c57c96905483", "rust_version": "1.67"}, {"timestamp": "2023-03-09 06:41:00", "name": "channel-rust-1.68.0.toml", "url": "https://static.rust-lang.org/dist/channel-rust-1.68.0.toml", "commit_hash": "2c8cc343237b8f7d5a3c3703e3a87f2eb2c54a74", "rust_version": "1.68.0"}, {"timestamp": "2023-03-23 07:16:49", "name": "channel-rust-1.68.1.toml", "url": "https://static.rust-lang.org/dist/channel-rust-1.68.1.toml", "commit_hash": "8460ca823e8367a30dda430efda790588b8c84d3", "rust_version": "1.68.1"}, {"timestamp": "2023-03-28 05:51:38", "name": "channel-rust-1.68.2.toml", "url": "https://static.rust-lang.org/dist/channel-rust-1.68.2.toml", "commit_hash": "9eb3afe9ebe9c7d2b84b71002d44f4a0edac95e0", "rust_version": "1.68.2"}, {"timestamp": "2023-03-28 05:51:38", "name": "channel-rust-1.68.toml", "url": "https://static.rust-lang.org/dist/channel-rust-1.68.toml", "commit_hash": "9eb3afe9ebe9c7d2b84b71002d44f4a0edac95e0", "rust_version": "1.68"}, {"timestamp": "2023-04-20 07:35:30", "name": "channel-rust-1.69.0.toml", "url": "https://static.rust-lang.org/dist/channel-rust-1.69.0.toml", "commit_hash": "84c898d65adf2f39a5a98507f1fe0ce10a2b8dbc", "rust_version": "1.69.0"}, {"timestamp": "2023-04-20 07:35:30", "name": "channel-rust-1.69.toml", "url": "https://static.rust-lang.org/dist/channel-rust-1.69.toml", "commit_hash": "84c898d65adf2f39a5a98507f1fe0ce10a2b8dbc", "rust_version": "1.69"}, {"timestamp": "2023-06-01 11:48:20", "name": "channel-rust-1.70.0.toml", "url": "https://static.rust-lang.org/dist/channel-rust-1.70.0.toml", "commit_hash": "90c541806f23a127002de5b4038be731ba1458ca", "rust_version": "1.70.0"}, {"timestamp": "2023-06-01 11:48:23", "name": "channel-rust-1.70.toml", "url": "https://static.rust-lang.org/dist/channel-rust-1.70.toml", "commit_hash": "90c541806f23a127002de5b4038be731ba1458ca", "rust_version": "1.70"}, {"timestamp": "2023-07-13 06:59:35", "name": "channel-rust-1.71.0.toml", "url": "https://static.rust-lang.org/dist/channel-rust-1.71.0.toml", "commit_hash": "8ede3aae28fe6e4d52b38157d7bfe0d3bceef225", "rust_version": "1.71.0"}, {"timestamp": "2023-08-03 11:06:55", "name": "channel-rust-1.71.1.toml", "url": "https://static.rust-lang.org/dist/channel-rust-1.71.1.toml", "commit_hash": "eb26296b556cef10fb713a38f3d16b9886080f26", "rust_version": "1.71.1"}, {"timestamp": "2023-08-03 11:06:55", "name": "channel-rust-1.71.toml", "url": "https://static.rust-lang.org/dist/channel-rust-1.71.toml", "commit_hash": "eb26296b556cef10fb713a38f3d16b9886080f26", "rust_version": "1.71"}, {"timestamp": "2023-08-24 06:42:47", "name": "channel-rust-1.72.0.toml", "url": "https://static.rust-lang.org/dist/channel-rust-1.72.0.toml", "commit_hash": "5680fa18feaa87f3ff04063800aec256c3d4b4be", "rust_version": "1.72.0"}, {"timestamp": "2023-09-19 07:02:18", "name": "channel-rust-1.72.1.toml", "url": "https://static.rust-lang.org/dist/channel-rust-1.72.1.toml", "commit_hash": "d5c2e9c342b358556da91d61ed4133f6f50fc0c3", "rust_version": "1.72.1"}, {"timestamp": "2023-09-19 07:02:18", "name": "channel-rust-1.72.toml", "url": "https://static.rust-lang.org/dist/channel-rust-1.72.toml", "commit_hash": "d5c2e9c342b358556da91d61ed4133f6f50fc0c3", "rust_version": "1.72"}, {"timestamp": "2023-10-05 09:06:42", "name": "channel-rust-1.73.0.toml", "url": "https://static.rust-lang.org/dist/channel-rust-1.73.0.toml", "commit_hash": "cc66ad468955717ab92600c770da8c1601a4ff33", "rust_version": "1.73.0"}, {"timestamp": "2023-10-05 09:06:42", "name": "channel-rust-1.73.toml", "url": "https://static.rust-lang.org/dist/channel-rust-1.73.toml", "commit_hash": "cc66ad468955717ab92600c770da8c1601a4ff33", "rust_version": "1.73"}, {"timestamp": "2023-11-16 05:45:13", "name": "channel-rust-1.74.0.toml", "url": "https://static.rust-lang.org/dist/channel-rust-1.74.0.toml", "commit_hash": "79e9716c980570bfd1f666e3b16ac583f0168962", "rust_version": "1.74.0"}, {"timestamp": "2023-12-07 06:17:53", "name": "channel-rust-1.74.1.toml", "url": "https://static.rust-lang.org/dist/channel-rust-1.74.1.toml", "commit_hash": "a28077b28a02b92985b3a3faecf92813155f1ea1", "rust_version": "1.74.1"}, {"timestamp": "2023-12-07 06:17:53", "name": "channel-rust-1.74.toml", "url": "https://static.rust-lang.org/dist/channel-rust-1.74.toml", "commit_hash": "a28077b28a02b92985b3a3faecf92813155f1ea1", "rust_version": "1.74"}, {"timestamp": "2023-12-16 17:22:32", "name": "channel-rust-1.75-beta.toml", "url": "https://static.rust-lang.org/dist/channel-rust-1.75-beta.toml", "commit_hash": "b216e7b0e7a2bdf11300a21a614dac6be3e99c5b", "rust_version": "1.75-beta"}, {"timestamp": "2023-11-12 17:26:44", "name": "channel-rust-1.75.0-beta.1.toml", "url": "https://static.rust-lang.org/dist/channel-rust-1.75.0-beta.1.toml", "commit_hash": "782883f609713fe9617ba64d90086742ec62d374", "rust_version": "1.75.0-beta.1"}, {"timestamp": "2023-11-18 17:23:59", "name": "channel-rust-1.75.0-beta.2.toml", "url": "https://static.rust-lang.org/dist/channel-rust-1.75.0-beta.2.toml", "commit_hash": "1bd723f02736102a893f9ded7243fe03d80c2954", "rust_version": "1.75.0-beta.2"}, {"timestamp": "2023-11-20 17:26:01", "name": "channel-rust-1.75.0-beta.3.toml", "url": "https://static.rust-lang.org/dist/channel-rust-1.75.0-beta.3.toml", "commit_hash": "b66b7951b9b4258fc433f2919e72598fbcc1816e", "rust_version": "1.75.0-beta.3"}, {"timestamp": "2023-11-28 17:28:13", "name": "channel-rust-1.75.0-beta.4.toml", "url": "https://static.rust-lang.org/dist/channel-rust-1.75.0-beta.4.toml", "commit_hash": "bd45872d96b0866775cd99ce94fc4462647e50f3", "rust_version": "1.75.0-beta.4"}, {"timestamp": "2023-12-01 17:26:24", "name": "channel-rust-1.75.0-beta.5.toml", "url": "https://static.rust-lang.org/dist/channel-rust-1.75.0-beta.5.toml", "commit_hash": "1a06ac5b5d7c9331e8de1aa1fd7e9d3533034b44", "rust_version": "1.75.0-beta.5"}, {"timestamp": "2023-12-13 17:20:44", "name": "channel-rust-1.75.0-beta.6.toml", "url": "https://static.rust-lang.org/dist/channel-rust-1.75.0-beta.6.toml", "commit_hash": "4bd9c37dc18d120ba5f307d8ddb07d733166227a", "rust_version": "1.75.0-beta.6"}, {"timestamp": "2023-12-16 17:22:32", "name": "channel-rust-1.75.0-beta.7.toml", "url": "https://static.rust-lang.org/dist/channel-rust-1.75.0-beta.7.toml", "commit_hash": "b216e7b0e7a2bdf11300a21a614dac6be3e99c5b", "rust_version": "1.75.0-beta.7"}, {"timestamp": "2023-12-16 17:22:33", "name": "channel-rust-1.75.0-beta.toml", "url": "https://static.rust-lang.org/dist/channel-rust-1.75.0-beta.toml", "commit_hash": "b216e7b0e7a2bdf11300a21a614dac6be3e99c5b", "rust_version": "1.75.0-beta"}, {"timestamp": "2023-12-28 08:17:50", "name": "channel-rust-1.75.0.toml", "url": "https://static.rust-lang.org/dist/channel-rust-1.75.0.toml", "commit_hash": "82e1608dfa6e0b5569232559e3d385fea5a93112", "rust_version": "1.75.0"}, {"timestamp": "2023-12-28 08:17:53", "name": "channel-rust-1.75.toml", "url": "https://static.rust-lang.org/dist/channel-rust-1.75.toml", "commit_hash": "82e1608dfa6e0b5569232559e3d385fea5a93112", "rust_version": "1.75"}, {"timestamp": "2024-01-27 17:20:40", "name": "channel-rust-1.76-beta.toml", "url": "https://static.rust-lang.org/dist/channel-rust-1.76-beta.toml", "commit_hash": "1633e2ae0630d21e668ce0a17f6268dfedf6becd", "rust_version": "1.76-beta"}, {"timestamp": "2023-12-21 17:20:01", "name": "channel-rust-1.76.0-beta.1.toml", "url": "https://static.rust-lang.org/dist/channel-rust-1.76.0-beta.1.toml", "commit_hash": "0e09125c6c3c2fd70d7de961bcf0e51575235fad", "rust_version": "1.76.0-beta.1"}, {"timestamp": "2024-01-08 17:22:43", "name": "channel-rust-1.76.0-beta.2.toml", "url": "https://static.rust-lang.org/dist/channel-rust-1.76.0-beta.2.toml", "commit_hash": "650745ceb2ae60e04f8cd7bfb671fc37239533e4", "rust_version": "1.76.0-beta.2"}, {"timestamp": "2024-01-10 17:21:35", "name": "channel-rust-1.76.0-beta.3.toml", "url": "https://static.rust-lang.org/dist/channel-rust-1.76.0-beta.3.toml", "commit_hash": "3a3478ec4f1acb7c16292eb2f44069f943525728", "rust_version": "1.76.0-beta.3"}, {"timestamp": "2024-01-11 17:20:20", "name": "channel-rust-1.76.0-beta.4.toml", "url": "https://static.rust-lang.org/dist/channel-rust-1.76.0-beta.4.toml", "commit_hash": "7bcd95c596cb5737508453a3a97f788106e30a4d", "rust_version": "1.76.0-beta.4"}, {"timestamp": "2024-01-12 17:24:47", "name": "channel-rust-1.76.0-beta.5.toml", "url": "https://static.rust-lang.org/dist/channel-rust-1.76.0-beta.5.toml", "commit_hash": "f732c37b4175158d3af9e2e156142ffb0bff8969", "rust_version": "1.76.0-beta.5"}, {"timestamp": "2024-01-20 17:28:14", "name": "channel-rust-1.76.0-beta.6.toml", "url": "https://static.rust-lang.org/dist/channel-rust-1.76.0-beta.6.toml", "commit_hash": "a2411cb8f98add54629633fb0764f134330b0c70", "rust_version": "1.76.0-beta.6"}, {"timestamp": "2024-01-22 17:23:06", "name": "channel-rust-1.76.0-beta.7.toml", "url": "https://static.rust-lang.org/dist/channel-rust-1.76.0-beta.7.toml", "commit_hash": "e8b6db72515807fa301ff8d39b8ac058d5653fd1", "rust_version": "1.76.0-beta.7"}, {"timestamp": "2024-01-24 17:17:17", "name": "channel-rust-1.76.0-beta.8.toml", "url": "https://static.rust-lang.org/dist/channel-rust-1.76.0-beta.8.toml", "commit_hash": "a27ad23393060264b5be0a09b73d17a843d69689", "rust_version": "1.76.0-beta.8"}, {"timestamp": "2024-01-27 17:20:40", "name": "channel-rust-1.76.0-beta.9.toml", "url": "https://static.rust-lang.org/dist/channel-rust-1.76.0-beta.9.toml", "commit_hash": "1633e2ae0630d21e668ce0a17f6268dfedf6becd", "rust_version": "1.76.0-beta.9"}, {"timestamp": "2024-01-27 17:20:40", "name": "channel-rust-1.76.0-beta.toml", "url": "https://static.rust-lang.org/dist/channel-rust-1.76.0-beta.toml", "commit_hash": "1633e2ae0630d21e668ce0a17f6268dfedf6becd", "rust_version": "1.76.0-beta"}, {"timestamp": "2024-02-08 06:02:51", "name": "channel-rust-1.76.0.toml", "url": "https://static.rust-lang.org/dist/channel-rust-1.76.0.toml", "commit_hash": "07dca489ac2d933c78d3c5158e3f43beefeb02ce", "rust_version": "1.76.0"}, {"timestamp": "2024-02-08 06:02:51", "name": "channel-rust-1.76.toml", "url": "https://static.rust-lang.org/dist/channel-rust-1.76.toml", "commit_hash": "07dca489ac2d933c78d3c5158e3f43beefeb02ce", "rust_version": "1.76"}, {"timestamp": "2024-03-16 18:21:29", "name": "channel-rust-1.77-beta.toml", "url": "https://static.rust-lang.org/dist/channel-rust-1.77-beta.toml", "commit_hash": "28fd269a50a79280e7576986e11081d987072c10", "rust_version": "1.77-beta"}, {"timestamp": "2024-02-04 08:29:59", "name": "channel-rust-1.77.0-beta.1.toml", "url": "https://static.rust-lang.org/dist/channel-rust-1.77.0-beta.1.toml", "commit_hash": "04ba4521971a83d71477a406b5ce7a479e9d7af8", "rust_version": "1.77.0-beta.1"}, {"timestamp": "2024-02-09 17:17:34", "name": "channel-rust-1.77.0-beta.2.toml", "url": "https://static.rust-lang.org/dist/channel-rust-1.77.0-beta.2.toml", "commit_hash": "f2048098a1ca42a520e7bed68e321a66edc0a1b1", "rust_version": "1.77.0-beta.2"}, {"timestamp": "2024-02-12 17:22:10", "name": "channel-rust-1.77.0-beta.3.toml", "url": "https://static.rust-lang.org/dist/channel-rust-1.77.0-beta.3.toml", "commit_hash": "3d66104851cc6aa90f53790ebb5014dbad27b9e5", "rust_version": "1.77.0-beta.3"}, {"timestamp": "2024-02-16 17:19:57", "name": "channel-rust-1.77.0-beta.4.toml", "url": "https://static.rust-lang.org/dist/channel-rust-1.77.0-beta.4.toml", "commit_hash": "d783f371bc5dcae26d1306c0c8fd4bedd4e79689", "rust_version": "1.77.0-beta.4"}, {"timestamp": "2024-02-17 17:21:21", "name": "channel-rust-1.77.0-beta.5.toml", "url": "https://static.rust-lang.org/dist/channel-rust-1.77.0-beta.5.toml", "commit_hash": "f2043422f7b161a2fc1a00589a8c4956db963450", "rust_version": "1.77.0-beta.5"}, {"timestamp": "2024-03-01 17:17:28", "name": "channel-rust-1.77.0-beta.6.toml", "url": "https://static.rust-lang.org/dist/channel-rust-1.77.0-beta.6.toml", "commit_hash": "2c9c764110ebbaffa2e248628ef8da36b69727bf", "rust_version": "1.77.0-beta.6"}, {"timestamp": "2024-03-06 17:18:58", "name": "channel-rust-1.77.0-beta.7.toml", "url": "https://static.rust-lang.org/dist/channel-rust-1.77.0-beta.7.toml", "commit_hash": "339fb6965026c4260d38ab6fd61cfcbecffd8279", "rust_version": "1.77.0-beta.7"}, {"timestamp": "2024-03-15 18:23:04", "name": "channel-rust-1.77.0-beta.8.toml", "url": "https://static.rust-lang.org/dist/channel-rust-1.77.0-beta.8.toml", "commit_hash": "2bcca41ad81146744295fada789a2699c72f69ac", "rust_version": "1.77.0-beta.8"}, {"timestamp": "2024-03-16 18:21:29", "name": "channel-rust-1.77.0-beta.9.toml", "url": "https://static.rust-lang.org/dist/channel-rust-1.77.0-beta.9.toml", "commit_hash": "28fd269a50a79280e7576986e11081d987072c10", "rust_version": "1.77.0-beta.9"}, {"timestamp": "2024-03-16 18:21:29", "name": "channel-rust-1.77.0-beta.toml", "url": "https://static.rust-lang.org/dist/channel-rust-1.77.0-beta.toml", "commit_hash": "28fd269a50a79280e7576986e11081d987072c10", "rust_version": "1.77.0-beta"}, {"timestamp": "2024-03-21 05:53:00", "name": "channel-rust-1.77.0.toml", "url": "https://static.rust-lang.org/dist/channel-rust-1.77.0.toml", "commit_hash": "aedd173a2c086e558c2b66d3743b344f977621a7", "rust_version": "1.77.0"}, {"timestamp": "2024-03-28 05:18:33", "name": "channel-rust-1.77.1.toml", "url": "https://static.rust-lang.org/dist/channel-rust-1.77.1.toml", "commit_hash": "7cf61ebde7b22796c69757901dd346d0fe70bd97", "rust_version": "1.77.1"}, {"timestamp": "2024-04-09 14:35:04", "name": "channel-rust-1.77.2.toml", "url": "https://static.rust-lang.org/dist/channel-rust-1.77.2.toml", "commit_hash": "25ef9e3d85d934b27d9dada2f9dd52b1dc63bb04", "rust_version": "1.77.2"}, {"timestamp": "2024-04-09 14:35:05", "name": "channel-rust-1.77.toml", "url": "https://static.rust-lang.org/dist/channel-rust-1.77.toml", "commit_hash": "25ef9e3d85d934b27d9dada2f9dd52b1dc63bb04", "rust_version": "1.77"}, {"timestamp": "2024-04-27 18:22:14", "name": "channel-rust-1.78-beta.toml", "url": "https://static.rust-lang.org/dist/channel-rust-1.78-beta.toml", "commit_hash": "b7e3de2fd9cd5b27f7e5949004b274af949814f6", "rust_version": "1.78-beta"}, {"timestamp": "2024-03-18 18:22:22", "name": "channel-rust-1.78.0-beta.1.toml", "url": "https://static.rust-lang.org/dist/channel-rust-1.78.0-beta.1.toml", "commit_hash": "efd9d2df12b5e17fac0b4d0fb89f612ecd79f259", "rust_version": "1.78.0-beta.1"}, {"timestamp": "2024-04-27 18:22:15", "name": "channel-rust-1.78.0-beta.10.toml", "url": "https://static.rust-lang.org/dist/channel-rust-1.78.0-beta.10.toml", "commit_hash": "b7e3de2fd9cd5b27f7e5949004b274af949814f6", "rust_version": "1.78.0-beta.10"}, {"timestamp": "2024-03-23 18:20:48", "name": "channel-rust-1.78.0-beta.2.toml", "url": "https://static.rust-lang.org/dist/channel-rust-1.78.0-beta.2.toml", "commit_hash": "277d06bc95c6c38a2337ccde798b2c709384bd84", "rust_version": "1.78.0-beta.2"}, {"timestamp": "2024-03-27 18:24:40", "name": "channel-rust-1.78.0-beta.3.toml", "url": "https://static.rust-lang.org/dist/channel-rust-1.78.0-beta.3.toml", "commit_hash": "4147533e05ee20c4fcc432736e7feeafa46521cd", "rust_version": "1.78.0-beta.3"}, {"timestamp": "2024-03-29 18:23:51", "name": "channel-rust-1.78.0-beta.4.toml", "url": "https://static.rust-lang.org/dist/channel-rust-1.78.0-beta.4.toml", "commit_hash": "c1195518c8ad7f37d15ecb82f39dec3da97f9c2f", "rust_version": "1.78.0-beta.4"}, {"timestamp": "2024-04-06 18:19:50", "name": "channel-rust-1.78.0-beta.5.toml", "url": "https://static.rust-lang.org/dist/channel-rust-1.78.0-beta.5.toml", "commit_hash": "9eff5103597e0ce73244028c96c75866dbcbad1d", "rust_version": "1.78.0-beta.5"}, {"timestamp": "2024-04-10 18:19:13", "name": "channel-rust-1.78.0-beta.6.toml", "url": "https://static.rust-lang.org/dist/channel-rust-1.78.0-beta.6.toml", "commit_hash": "27011d5dc09a8d1ac2289d024f54ecac9fc70d47", "rust_version": "1.78.0-beta.6"}, {"timestamp": "2024-04-12 18:23:16", "name": "channel-rust-1.78.0-beta.7.toml", "url": "https://static.rust-lang.org/dist/channel-rust-1.78.0-beta.7.toml", "commit_hash": "6fd1912922a7b468b1875d16571bb7a00d5df93f", "rust_version": "1.78.0-beta.7"}, {"timestamp": "2024-04-19 18:22:01", "name": "channel-rust-1.78.0-beta.8.toml", "url": "https://static.rust-lang.org/dist/channel-rust-1.78.0-beta.8.toml", "commit_hash": "13ef05e2be9862ea7b94d0b42e0b2d044b3c7f6b", "rust_version": "1.78.0-beta.8"}, {"timestamp": "2024-04-23 18:21:11", "name": "channel-rust-1.78.0-beta.9.toml", "url": "https://static.rust-lang.org/dist/channel-rust-1.78.0-beta.9.toml", "commit_hash": "205af5d6beedc895b7f1fa2cdcae634bc2754cce", "rust_version": "1.78.0-beta.9"}, {"timestamp": "2024-04-27 18:22:15", "name": "channel-rust-1.78.0-beta.toml", "url": "https://static.rust-lang.org/dist/channel-rust-1.78.0-beta.toml", "commit_hash": "b7e3de2fd9cd5b27f7e5949004b274af949814f6", "rust_version": "1.78.0-beta"}, {"timestamp": "2024-05-02 05:34:25", "name": "channel-rust-1.78.0.toml", "url": "https://static.rust-lang.org/dist/channel-rust-1.78.0.toml", "commit_hash": "9b00956e56009bab2aa15d7bff10916599e3d6d6", "rust_version": "1.78.0"}, {"timestamp": "2024-05-02 05:34:24", "name": "channel-rust-1.78.toml", "url": "https://static.rust-lang.org/dist/channel-rust-1.78.toml", "commit_hash": "9b00956e56009bab2aa15d7bff10916599e3d6d6", "rust_version": "1.78"}, {"timestamp": "2024-06-07 18:23:25", "name": "channel-rust-1.79-beta.toml", "url": "https://static.rust-lang.org/dist/channel-rust-1.79-beta.toml", "commit_hash": "7bb6510fc1899b008837a376a7fdf31b341cc1bb", "rust_version": "1.79-beta"}, {"timestamp": "2024-04-28 18:20:34", "name": "channel-rust-1.79.0-beta.1.toml", "url": "https://static.rust-lang.org/dist/channel-rust-1.79.0-beta.1.toml", "commit_hash": "6b544f5ff8d45221d61962651a5f5ab9fe535e16", "rust_version": "1.79.0-beta.1"}, {"timestamp": "2024-06-07 18:23:25", "name": "channel-rust-1.79.0-beta.10.toml", "url": "https://static.rust-lang.org/dist/channel-rust-1.79.0-beta.10.toml", "commit_hash": "7bb6510fc1899b008837a376a7fdf31b341cc1bb", "rust_version": "1.79.0-beta.10"}, {"timestamp": "2024-05-02 18:19:29", "name": "channel-rust-1.79.0-beta.2.toml", "url": "https://static.rust-lang.org/dist/channel-rust-1.79.0-beta.2.toml", "commit_hash": "4bf9354b9e6f07fc6dd881a2d313be0f63cdb8cb", "rust_version": "1.79.0-beta.2"}, {"timestamp": "2024-05-03 18:22:44", "name": "channel-rust-1.79.0-beta.3.toml", "url": "https://static.rust-lang.org/dist/channel-rust-1.79.0-beta.3.toml", "commit_hash": "f5d04caa74a1dfa5ffc4082c2c8f621f25336bbc", "rust_version": "1.79.0-beta.3"}, {"timestamp": "2024-05-10 18:23:12", "name": "channel-rust-1.79.0-beta.4.toml", "url": "https://static.rust-lang.org/dist/channel-rust-1.79.0-beta.4.toml", "commit_hash": "a26981974230110fa8fb15e1cf04d05b9a2103f9", "rust_version": "1.79.0-beta.4"}, {"timestamp": "2024-05-17 18:19:22", "name": "channel-rust-1.79.0-beta.5.toml", "url": "https://static.rust-lang.org/dist/channel-rust-1.79.0-beta.5.toml", "commit_hash": "0436bf18fce724968645d0d2af782ad22f0774d7", "rust_version": "1.79.0-beta.5"}, {"timestamp": "2024-05-23 18:20:50", "name": "channel-rust-1.79.0-beta.6.toml", "url": "https://static.rust-lang.org/dist/channel-rust-1.79.0-beta.6.toml", "commit_hash": "66eb3e404b81e916f5e6d4755fce73800b0cb4c2", "rust_version": "1.79.0-beta.6"}, {"timestamp": "2024-05-25 18:22:54", "name": "channel-rust-1.79.0-beta.7.toml", "url": "https://static.rust-lang.org/dist/channel-rust-1.79.0-beta.7.toml", "commit_hash": "d9e85b56e7f85f7fdabff71f217b7bb2cee0ef68", "rust_version": "1.79.0-beta.7"}, {"timestamp": "2024-06-03 18:25:57", "name": "channel-rust-1.79.0-beta.8.toml", "url": "https://static.rust-lang.org/dist/channel-rust-1.79.0-beta.8.toml", "commit_hash": "d0f44a4cf3d25688be1f6dc4d67eabbbbca25609", "rust_version": "1.79.0-beta.8"}, {"timestamp": "2024-06-04 18:20:45", "name": "channel-rust-1.79.0-beta.9.toml", "url": "https://static.rust-lang.org/dist/channel-rust-1.79.0-beta.9.toml", "commit_hash": "81ed1ceb38e9a4bc01b6c84a92c87b34f7abe18d", "rust_version": "1.79.0-beta.9"}, {"timestamp": "2024-06-07 18:23:25", "name": "channel-rust-1.79.0-beta.toml", "url": "https://static.rust-lang.org/dist/channel-rust-1.79.0-beta.toml", "commit_hash": "7bb6510fc1899b008837a376a7fdf31b341cc1bb", "rust_version": "1.79.0-beta"}, {"timestamp": "2024-06-13 07:00:18", "name": "channel-rust-1.79.0.toml", "url": "https://static.rust-lang.org/dist/channel-rust-1.79.0.toml", "commit_hash": "129f3b9964af4d4a709d1383930ade12dfe7c081", "rust_version": "1.79.0"}, {"timestamp": "2024-06-13 07:00:18", "name": "channel-rust-1.79.toml", "url": "https://static.rust-lang.org/dist/channel-rust-1.79.toml", "commit_hash": "129f3b9964af4d4a709d1383930ade12dfe7c081", "rust_version": "1.79"}, {"timestamp": "2024-07-20 18:19:58", "name": "channel-rust-1.80-beta.toml", "url": "https://static.rust-lang.org/dist/channel-rust-1.80-beta.toml", "commit_hash": "7466ba077d7454d5a81e1a3dcbd1b5bac3704e3d", "rust_version": "1.80-beta"}, {"timestamp": "2024-06-10 18:20:19", "name": "channel-rust-1.80.0-beta.1.toml", "url": "https://static.rust-lang.org/dist/channel-rust-1.80.0-beta.1.toml", "commit_hash": "75ac3b6331873133c4f7a10f2252afd6f3906c6a", "rust_version": "1.80.0-beta.1"}, {"timestamp": "2024-06-13 18:23:00", "name": "channel-rust-1.80.0-beta.2.toml", "url": "https://static.rust-lang.org/dist/channel-rust-1.80.0-beta.2.toml", "commit_hash": "544e5fb73eea7aad7742cb0ed6c6bc14fdfae934", "rust_version": "1.80.0-beta.2"}, {"timestamp": "2024-06-14 18:24:26", "name": "channel-rust-1.80.0-beta.3.toml", "url": "https://static.rust-lang.org/dist/channel-rust-1.80.0-beta.3.toml", "commit_hash": "105fc5ccc942631c367a53a902c57f45ea534d35", "rust_version": "1.80.0-beta.3"}, {"timestamp": "2024-06-21 18:20:57", "name": "channel-rust-1.80.0-beta.4.toml", "url": "https://static.rust-lang.org/dist/channel-rust-1.80.0-beta.4.toml", "commit_hash": "64a1fe67112931359c7c9a222f08fd206255c2b5", "rust_version": "1.80.0-beta.4"}, {"timestamp": "2024-07-06 18:21:52", "name": "channel-rust-1.80.0-beta.5.toml", "url": "https://static.rust-lang.org/dist/channel-rust-1.80.0-beta.5.toml", "commit_hash": "e5da71fca9bed167576232912271d7366e29bbc6", "rust_version": "1.80.0-beta.5"}, {"timestamp": "2024-07-12 18:21:58", "name": "channel-rust-1.80.0-beta.6.toml", "url": "https://static.rust-lang.org/dist/channel-rust-1.80.0-beta.6.toml", "commit_hash": "b8b9158f2c4e7ea5a09361def282067fa55c782d", "rust_version": "1.80.0-beta.6"}, {"timestamp": "2024-07-18 18:23:11", "name": "channel-rust-1.80.0-beta.7.toml", "url": "https://static.rust-lang.org/dist/channel-rust-1.80.0-beta.7.toml", "commit_hash": "3ad5ec81fdfbfefda2b594da618e6d4f25e66792", "rust_version": "1.80.0-beta.7"}, {"timestamp": "2024-07-19 18:23:03", "name": "channel-rust-1.80.0-beta.8.toml", "url": "https://static.rust-lang.org/dist/channel-rust-1.80.0-beta.8.toml", "commit_hash": "b06e8ad97074a624afaebea9117aef79f4f95ca1", "rust_version": "1.80.0-beta.8"}, {"timestamp": "2024-07-20 18:19:58", "name": "channel-rust-1.80.0-beta.9.toml", "url": "https://static.rust-lang.org/dist/channel-rust-1.80.0-beta.9.toml", "commit_hash": "7466ba077d7454d5a81e1a3dcbd1b5bac3704e3d", "rust_version": "1.80.0-beta.9"}, {"timestamp": "2024-07-20 18:19:56", "name": "channel-rust-1.80.0-beta.toml", "url": "https://static.rust-lang.org/dist/channel-rust-1.80.0-beta.toml", "commit_hash": "7466ba077d7454d5a81e1a3dcbd1b5bac3704e3d", "rust_version": "1.80.0-beta"}, {"timestamp": "2024-07-25 04:58:10", "name": "channel-rust-1.80.0.toml", "url": "https://static.rust-lang.org/dist/channel-rust-1.80.0.toml", "commit_hash": "051478957371ee0084a7c0913941d2a8c4757bb9", "rust_version": "1.80.0"}, {"timestamp": "2024-08-08 07:03:19", "name": "channel-rust-1.80.1.toml", "url": "https://static.rust-lang.org/dist/channel-rust-1.80.1.toml", "commit_hash": "3f5fd8dd41153bc5fdca9427e9e05be2c767ba23", "rust_version": "1.80.1"}, {"timestamp": "2024-08-08 07:03:19", "name": "channel-rust-1.80.toml", "url": "https://static.rust-lang.org/dist/channel-rust-1.80.toml", "commit_hash": "3f5fd8dd41153bc5fdca9427e9e05be2c767ba23", "rust_version": "1.80"}, {"timestamp": "2024-09-01 18:26:08", "name": "channel-rust-1.81-beta.toml", "url": "https://static.rust-lang.org/dist/channel-rust-1.81-beta.toml", "commit_hash": "4a101b4b5db701edee2b705d1cc1c58c6058c43f", "rust_version": "1.81-beta"}, {"timestamp": "2024-07-22 18:27:00", "name": "channel-rust-1.81.0-beta.1.toml", "url": "https://static.rust-lang.org/dist/channel-rust-1.81.0-beta.1.toml", "commit_hash": "b13c0dda2448813feeb458735e548f9e793f2ff2", "rust_version": "1.81.0-beta.1"}, {"timestamp": "2024-07-25 18:22:55", "name": "channel-rust-1.81.0-beta.2.toml", "url": "https://static.rust-lang.org/dist/channel-rust-1.81.0-beta.2.toml", "commit_hash": "08328a323ecd80b443a8fcc72c6b1071f48e233f", "rust_version": "1.81.0-beta.2"}, {"timestamp": "2024-08-04 18:22:34", "name": "channel-rust-1.81.0-beta.3.toml", "url": "https://static.rust-lang.org/dist/channel-rust-1.81.0-beta.3.toml", "commit_hash": "4b55199142eab01ca1efcb7dd4c974c685d099d1", "rust_version": "1.81.0-beta.3"}, {"timestamp": "2024-08-05 18:25:22", "name": "channel-rust-1.81.0-beta.4.toml", "url": "https://static.rust-lang.org/dist/channel-rust-1.81.0-beta.4.toml", "commit_hash": "2059132d3c715514da0e4f9cd395a708e666e306", "rust_version": "1.81.0-beta.4"}, {"timestamp": "2024-08-15 18:22:53", "name": "channel-rust-1.81.0-beta.5.toml", "url": "https://static.rust-lang.org/dist/channel-rust-1.81.0-beta.5.toml", "commit_hash": "6c199c89c72db4c1912674f872eabd34753b19f8", "rust_version": "1.81.0-beta.5"}, {"timestamp": "2024-08-21 18:24:00", "name": "channel-rust-1.81.0-beta.6.toml", "url": "https://static.rust-lang.org/dist/channel-rust-1.81.0-beta.6.toml", "commit_hash": "b5fd9f6f1061b79c045cc08fe03e00caad536800", "rust_version": "1.81.0-beta.6"}, {"timestamp": "2024-08-28 18:22:12", "name": "channel-rust-1.81.0-beta.7.toml", "url": "https://static.rust-lang.org/dist/channel-rust-1.81.0-beta.7.toml", "commit_hash": "4a765c0b8754bdbc1d841d080e8c8a47ea774a80", "rust_version": "1.81.0-beta.7"}, {"timestamp": "2024-09-01 18:26:08", "name": "channel-rust-1.81.0-beta.8.toml", "url": "https://static.rust-lang.org/dist/channel-rust-1.81.0-beta.8.toml", "commit_hash": "4a101b4b5db701edee2b705d1cc1c58c6058c43f", "rust_version": "1.81.0-beta.8"}, {"timestamp": "2024-09-01 18:26:08", "name": "channel-rust-1.81.0-beta.toml", "url": "https://static.rust-lang.org/dist/channel-rust-1.81.0-beta.toml", "commit_hash": "4a101b4b5db701edee2b705d1cc1c58c6058c43f", "rust_version": "1.81.0-beta"}, {"timestamp": "2024-09-05 09:01:34", "name": "channel-rust-1.81.0.toml", "url": "https://static.rust-lang.org/dist/channel-rust-1.81.0.toml", "commit_hash": "eeb90cda1969383f56a2637cbd3037bdf598841c", "rust_version": "1.81.0"}, {"timestamp": "2024-09-05 09:01:34", "name": "channel-rust-1.81.toml", "url": "https://static.rust-lang.org/dist/channel-rust-1.81.toml", "commit_hash": "eeb90cda1969383f56a2637cbd3037bdf598841c", "rust_version": "1.81"}, {"timestamp": "2024-10-12 18:31:28", "name": "channel-rust-1.82-beta.toml", "url": "https://static.rust-lang.org/dist/channel-rust-1.82-beta.toml", "commit_hash": "763ad520cc6b831ec98e20f8a8fe85b160ad859d", "rust_version": "1.82-beta"}, {"timestamp": "2024-09-03 18:34:29", "name": "channel-rust-1.82.0-beta.1.toml", "url": "https://static.rust-lang.org/dist/channel-rust-1.82.0-beta.1.toml", "commit_hash": "fb1a6f7f4e154e5787e5410867cf07f7557360c1", "rust_version": "1.82.0-beta.1"}, {"timestamp": "2024-09-04 18:32:05", "name": "channel-rust-1.82.0-beta.2.toml", "url": "https://static.rust-lang.org/dist/channel-rust-1.82.0-beta.2.toml", "commit_hash": "c7c49f44a7bb561dd9317e14908a1e50fa478ce5", "rust_version": "1.82.0-beta.2"}, {"timestamp": "2024-09-09 18:32:27", "name": "channel-rust-1.82.0-beta.3.toml", "url": "https://static.rust-lang.org/dist/channel-rust-1.82.0-beta.3.toml", "commit_hash": "4976ae480e2b29cc46f44e1b9914469cc384fcc9", "rust_version": "1.82.0-beta.3"}, {"timestamp": "2024-09-21 18:34:33", "name": "channel-rust-1.82.0-beta.4.toml", "url": "https://static.rust-lang.org/dist/channel-rust-1.82.0-beta.4.toml", "commit_hash": "8c27a2ba6b21f3406a51118643080f0591949827", "rust_version": "1.82.0-beta.4"}, {"timestamp": "2024-09-27 18:28:54", "name": "channel-rust-1.82.0-beta.5.toml", "url": "https://static.rust-lang.org/dist/channel-rust-1.82.0-beta.5.toml", "commit_hash": "6a3b69c6b0529151da5fb4568961519a80adccf9", "rust_version": "1.82.0-beta.5"}, {"timestamp": "2024-10-12 18:31:28", "name": "channel-rust-1.82.0-beta.6.toml", "url": "https://static.rust-lang.org/dist/channel-rust-1.82.0-beta.6.toml", "commit_hash": "763ad520cc6b831ec98e20f8a8fe85b160ad859d", "rust_version": "1.82.0-beta.6"}, {"timestamp": "2024-10-12 18:31:28", "name": "channel-rust-1.82.0-beta.toml", "url": "https://static.rust-lang.org/dist/channel-rust-1.82.0-beta.toml", "commit_hash": "763ad520cc6b831ec98e20f8a8fe85b160ad859d", "rust_version": "1.82.0-beta"}, {"timestamp": "2024-10-17 09:39:09", "name": "channel-rust-1.82.0.toml", "url": "https://static.rust-lang.org/dist/channel-rust-1.82.0.toml", "commit_hash": "f6e511eec7342f59a25f7c0534f1dbea00d01b14", "rust_version": "1.82.0"}, {"timestamp": "2024-10-17 09:39:09", "name": "channel-rust-1.82.toml", "url": "https://static.rust-lang.org/dist/channel-rust-1.82.toml", "commit_hash": "f6e511eec7342f59a25f7c0534f1dbea00d01b14", "rust_version": "1.82"}, {"timestamp": "2024-11-22 17:33:04", "name": "channel-rust-1.83-beta.toml", "url": "https://static.rust-lang.org/dist/channel-rust-1.83-beta.toml", "commit_hash": "b35ad722a4ba08afc544ebfd1c0b4eb5f964dd6b", "rust_version": "1.83-beta"}, {"timestamp": "2024-10-15 18:37:27", "name": "channel-rust-1.83.0-beta.1.toml", "url": "https://static.rust-lang.org/dist/channel-rust-1.83.0-beta.1.toml", "commit_hash": "0125edf41b8ce32db5c2cce0c83e32ad2e4dde17", "rust_version": "1.83.0-beta.1"}, {"timestamp": "2024-10-18 18:34:56", "name": "channel-rust-1.83.0-beta.2.toml", "url": "https://static.rust-lang.org/dist/channel-rust-1.83.0-beta.2.toml", "commit_hash": "88c1c3c1102bbf3860891bfa52b7ddd9f26aec2f", "rust_version": "1.83.0-beta.2"}, {"timestamp": "2024-10-31 18:33:39", "name": "channel-rust-1.83.0-beta.3.toml", "url": "https://static.rust-lang.org/dist/channel-rust-1.83.0-beta.3.toml", "commit_hash": "f41c7ed9889384b2689113d125cd38bca7157000", "rust_version": "1.83.0-beta.3"}, {"timestamp": "2024-11-02 18:37:03", "name": "channel-rust-1.83.0-beta.4.toml", "url": "https://static.rust-lang.org/dist/channel-rust-1.83.0-beta.4.toml", "commit_hash": "67512dee7a470ea7cdd6066d76bb95b7742e96e8", "rust_version": "1.83.0-beta.4"}, {"timestamp": "2024-11-08 17:38:04", "name": "channel-rust-1.83.0-beta.5.toml", "url": "https://static.rust-lang.org/dist/channel-rust-1.83.0-beta.5.toml", "commit_hash": "eb6e3fa1a226400015d13d14b4f6010e7710a2c9", "rust_version": "1.83.0-beta.5"}, {"timestamp": "2024-11-16 17:36:05", "name": "channel-rust-1.83.0-beta.6.toml", "url": "https://static.rust-lang.org/dist/channel-rust-1.83.0-beta.6.toml", "commit_hash": "4ff8ff0ecd982852e08e6af1223cee957d5b781e", "rust_version": "1.83.0-beta.6"}, {"timestamp": "2024-11-22 17:33:05", "name": "channel-rust-1.83.0-beta.7.toml", "url": "https://static.rust-lang.org/dist/channel-rust-1.83.0-beta.7.toml", "commit_hash": "b35ad722a4ba08afc544ebfd1c0b4eb5f964dd6b", "rust_version": "1.83.0-beta.7"}, {"timestamp": "2024-11-22 17:33:05", "name": "channel-rust-1.83.0-beta.toml", "url": "https://static.rust-lang.org/dist/channel-rust-1.83.0-beta.toml", "commit_hash": "b35ad722a4ba08afc544ebfd1c0b4eb5f964dd6b", "rust_version": "1.83.0-beta"}, {"timestamp": "2024-11-28 05:58:26", "name": "channel-rust-1.83.0.toml", "url": "https://static.rust-lang.org/dist/channel-rust-1.83.0.toml", "commit_hash": "90b35a6239c3d8bdabc530a6a0816f7ff89a0aaf", "rust_version": "1.83.0"}, {"timestamp": "2024-11-28 05:58:25", "name": "channel-rust-1.83.toml", "url": "https://static.rust-lang.org/dist/channel-rust-1.83.toml", "commit_hash": "90b35a6239c3d8bdabc530a6a0816f7ff89a0aaf", "rust_version": "1.83"}, {"timestamp": "2025-01-03 17:55:06", "name": "channel-rust-1.84-beta.toml", "url": "https://static.rust-lang.org/dist/channel-rust-1.84-beta.toml", "commit_hash": "953a5caef005993f93d8fe9baa344cc2591496c2", "rust_version": "1.84-beta"}, {"timestamp": "2024-11-26 17:53:28", "name": "channel-rust-1.84.0-beta.1.toml", "url": "https://static.rust-lang.org/dist/channel-rust-1.84.0-beta.1.toml", "commit_hash": "b4297a573b4eefacd62e7ea1ba071536282d3254", "rust_version": "1.84.0-beta.1"}, {"timestamp": "2024-11-30 17:55:22", "name": "channel-rust-1.84.0-beta.2.toml", "url": "https://static.rust-lang.org/dist/channel-rust-1.84.0-beta.2.toml", "commit_hash": "0f13036040380420ec928f5ca761ac5fbe6fef91", "rust_version": "1.84.0-beta.2"}, {"timestamp": "2024-12-02 17:53:12", "name": "channel-rust-1.84.0-beta.3.toml", "url": "https://static.rust-lang.org/dist/channel-rust-1.84.0-beta.3.toml", "commit_hash": "ea5e5ca0553095786f968671ab1c222e5b1df5c3", "rust_version": "1.84.0-beta.3"}, {"timestamp": "2024-12-07 17:53:43", "name": "channel-rust-1.84.0-beta.4.toml", "url": "https://static.rust-lang.org/dist/channel-rust-1.84.0-beta.4.toml", "commit_hash": "202008a1b8de96d2e5b6bc02d379db03a877d34d", "rust_version": "1.84.0-beta.4"}, {"timestamp": "2024-12-27 17:53:20", "name": "channel-rust-1.84.0-beta.5.toml", "url": "https://static.rust-lang.org/dist/channel-rust-1.84.0-beta.5.toml", "commit_hash": "0857a8e32cd55fca2e6c648e586f9ce46c22eb42", "rust_version": "1.84.0-beta.5"}, {"timestamp": "2025-01-03 17:55:06", "name": "channel-rust-1.84.0-beta.6.toml", "url": "https://static.rust-lang.org/dist/channel-rust-1.84.0-beta.6.toml", "commit_hash": "953a5caef005993f93d8fe9baa344cc2591496c2", "rust_version": "1.84.0-beta.6"}, {"timestamp": "2025-01-03 17:55:07", "name": "channel-rust-1.84.0-beta.toml", "url": "https://static.rust-lang.org/dist/channel-rust-1.84.0-beta.toml", "commit_hash": "953a5caef005993f93d8fe9baa344cc2591496c2", "rust_version": "1.84.0-beta"}, {"timestamp": "2025-01-09 07:38:04", "name": "channel-rust-1.84.0.toml", "url": "https://static.rust-lang.org/dist/channel-rust-1.84.0.toml", "commit_hash": "9fc6b43126469e3858e2fe86cafb4f0fd5068869", "rust_version": "1.84.0"}, {"timestamp": "2025-01-30 10:42:30", "name": "channel-rust-1.84.1.toml", "url": "https://static.rust-lang.org/dist/channel-rust-1.84.1.toml", "commit_hash": "e71f9a9a98b0faf423844bf0ba7438f29dc27d58", "rust_version": "1.84.1"}, {"timestamp": "2025-01-30 10:42:31", "name": "channel-rust-1.84.toml", "url": "https://static.rust-lang.org/dist/channel-rust-1.84.toml", "commit_hash": "e71f9a9a98b0faf423844bf0ba7438f29dc27d58", "rust_version": "1.84"}, {"timestamp": "2025-02-13 17:56:54", "name": "channel-rust-1.85-beta.toml", "url": "https://static.rust-lang.org/dist/channel-rust-1.85-beta.toml", "commit_hash": "461de7492e5354419cf27fe94b6aa235b4121927", "rust_version": "1.85-beta"}, {"timestamp": "2025-01-08 07:27:04", "name": "channel-rust-1.85.0-beta.1.toml", "url": "https://static.rust-lang.org/dist/channel-rust-1.85.0-beta.1.toml", "commit_hash": "e30eefff41038ceea427009023627d6d66b36715", "rust_version": "1.85.0-beta.1"}, {"timestamp": "2025-01-11 17:56:35", "name": "channel-rust-1.85.0-beta.2.toml", "url": "https://static.rust-lang.org/dist/channel-rust-1.85.0-beta.2.toml", "commit_hash": "fe9b9751fa54a5871b87cd36a582f9b7b06123fd", "rust_version": "1.85.0-beta.2"}, {"timestamp": "2025-01-17 17:58:06", "name": "channel-rust-1.85.0-beta.4.toml", "url": "https://static.rust-lang.org/dist/channel-rust-1.85.0-beta.4.toml", "commit_hash": "752fecf8005cd7a7ae8c0b74d0f8fc3cd3cd86fe", "rust_version": "1.85.0-beta.4"}, {"timestamp": "2025-01-20 17:57:04", "name": "channel-rust-1.85.0-beta.5.toml", "url": "https://static.rust-lang.org/dist/channel-rust-1.85.0-beta.5.toml", "commit_hash": "44165070434aab38db1115448621880a35da00ff", "rust_version": "1.85.0-beta.5"}, {"timestamp": "2025-01-26 17:57:50", "name": "channel-rust-1.85.0-beta.6.toml", "url": "https://static.rust-lang.org/dist/channel-rust-1.85.0-beta.6.toml", "commit_hash": "14445aaf35d45f62fddda8cb5027f44ba4316e7f", "rust_version": "1.85.0-beta.6"}, {"timestamp": "2025-02-01 17:56:53", "name": "channel-rust-1.85.0-beta.7.toml", "url": "https://static.rust-lang.org/dist/channel-rust-1.85.0-beta.7.toml", "commit_hash": "0277061b9a4096437b9b35f471c915e1cbe3128f", "rust_version": "1.85.0-beta.7"}, {"timestamp": "2025-02-07 17:59:05", "name": "channel-rust-1.85.0-beta.8.toml", "url": "https://static.rust-lang.org/dist/channel-rust-1.85.0-beta.8.toml", "commit_hash": "38213856a8a3a6d49a234e0d95a722a4f28a2b18", "rust_version": "1.85.0-beta.8"}, {"timestamp": "2025-02-13 17:56:54", "name": "channel-rust-1.85.0-beta.9.toml", "url": "https://static.rust-lang.org/dist/channel-rust-1.85.0-beta.9.toml", "commit_hash": "461de7492e5354419cf27fe94b6aa235b4121927", "rust_version": "1.85.0-beta.9"}, {"timestamp": "2025-02-13 17:56:55", "name": "channel-rust-1.85.0-beta.toml", "url": "https://static.rust-lang.org/dist/channel-rust-1.85.0-beta.toml", "commit_hash": "461de7492e5354419cf27fe94b6aa235b4121927", "rust_version": "1.85.0-beta"}, {"timestamp": "2025-02-20 09:05:49", "name": "channel-rust-1.85.0.toml", "url": "https://static.rust-lang.org/dist/channel-rust-1.85.0.toml", "commit_hash": "4d91de4e48198da2e33413efdcd9cd2cc0c46688", "rust_version": "1.85.0"}, {"timestamp": "2025-03-18 10:37:35", "name": "channel-rust-1.85.1.toml", "url": "https://static.rust-lang.org/dist/channel-rust-1.85.1.toml", "commit_hash": "4eb161250e340c8f48f66e2b929ef4a5bed7c181", "rust_version": "1.85.1"}, {"timestamp": "2025-03-18 10:37:35", "name": "channel-rust-1.85.toml", "url": "https://static.rust-lang.org/dist/channel-rust-1.85.toml", "commit_hash": "4eb161250e340c8f48f66e2b929ef4a5bed7c181", "rust_version": "1.85"}, {"timestamp": "2025-03-22 19:06:27", "name": "channel-rust-1.86-beta.toml", "url": "https://static.rust-lang.org/dist/channel-rust-1.86-beta.toml", "commit_hash": "7824ede68eef464473b01249568df27ed9e4fc27", "rust_version": "1.86-beta"}, {"timestamp": "2025-02-17 21:39:26", "name": "channel-rust-1.86.0-beta.1.toml", "url": "https://static.rust-lang.org/dist/channel-rust-1.86.0-beta.1.toml", "commit_hash": "f0cb41030579cd1a6f72bd23f38e677052d5d485", "rust_version": "1.86.0-beta.1"}, {"timestamp": "2025-02-24 18:09:05", "name": "channel-rust-1.86.0-beta.2.toml", "url": "https://static.rust-lang.org/dist/channel-rust-1.86.0-beta.2.toml", "commit_hash": "b678aabb38ba885943093328c1db7edd5fe6c791", "rust_version": "1.86.0-beta.2"}, {"timestamp": "2025-02-27 18:06:40", "name": "channel-rust-1.86.0-beta.3.toml", "url": "https://static.rust-lang.org/dist/channel-rust-1.86.0-beta.3.toml", "commit_hash": "42212a5c45ab623e38a36a74ea288a2b0277b911", "rust_version": "1.86.0-beta.3"}, {"timestamp": "2025-03-02 18:06:47", "name": "channel-rust-1.86.0-beta.4.toml", "url": "https://static.rust-lang.org/dist/channel-rust-1.86.0-beta.4.toml", "commit_hash": "61e1603ac7b9162968f55a4e9f6f136c0e1bf68a", "rust_version": "1.86.0-beta.4"}, {"timestamp": "2025-03-08 18:07:32", "name": "channel-rust-1.86.0-beta.5.toml", "url": "https://static.rust-lang.org/dist/channel-rust-1.86.0-beta.5.toml", "commit_hash": "b2af9a598e793de1f65afa6c14f7eb7545332ac1", "rust_version": "1.86.0-beta.5"}, {"timestamp": "2025-03-16 19:07:01", "name": "channel-rust-1.86.0-beta.6.toml", "url": "https://static.rust-lang.org/dist/channel-rust-1.86.0-beta.6.toml", "commit_hash": "8c7969a3ae4a292789a415618fd3ebd35bee38e9", "rust_version": "1.86.0-beta.6"}, {"timestamp": "2025-03-22 19:06:27", "name": "channel-rust-1.86.0-beta.7.toml", "url": "https://static.rust-lang.org/dist/channel-rust-1.86.0-beta.7.toml", "commit_hash": "7824ede68eef464473b01249568df27ed9e4fc27", "rust_version": "1.86.0-beta.7"}, {"timestamp": "2025-03-22 19:06:27", "name": "channel-rust-1.86.0-beta.toml", "url": "https://static.rust-lang.org/dist/channel-rust-1.86.0-beta.toml", "commit_hash": "7824ede68eef464473b01249568df27ed9e4fc27", "rust_version": "1.86.0-beta"}, {"timestamp": "2025-04-03 02:38:30", "name": "channel-rust-1.86.0.toml", "url": "https://static.rust-lang.org/dist/channel-rust-1.86.0.toml", "commit_hash": "05f9846f893b09a1be1fc8560e33fc3c815cfecb", "rust_version": "1.86.0"}, {"timestamp": "2025-04-03 02:38:30", "name": "channel-rust-1.86.toml", "url": "https://static.rust-lang.org/dist/channel-rust-1.86.toml", "commit_hash": "05f9846f893b09a1be1fc8560e33fc3c815cfecb", "rust_version": "1.86"}, {"timestamp": "2025-05-07 19:19:44", "name": "channel-rust-1.87-beta.toml", "url": "https://static.rust-lang.org/dist/channel-rust-1.87-beta.toml", "commit_hash": "af91af44eb85ceac634afa72cc73be4af358b350", "rust_version": "1.87-beta"}, {"timestamp": "2025-04-01 19:23:18", "name": "channel-rust-1.87.0-beta.1.toml", "url": "https://static.rust-lang.org/dist/channel-rust-1.87.0-beta.1.toml", "commit_hash": "45165c82a4c5315ff52c391ad138f41ff40b52d8", "rust_version": "1.87.0-beta.1"}, {"timestamp": "2025-04-05 19:20:54", "name": "channel-rust-1.87.0-beta.2.toml", "url": "https://static.rust-lang.org/dist/channel-rust-1.87.0-beta.2.toml", "commit_hash": "e6ed56aad81a8bc50c403535370164132e96bb08", "rust_version": "1.87.0-beta.2"}, {"timestamp": "2025-04-07 19:20:26", "name": "channel-rust-1.87.0-beta.3.toml", "url": "https://static.rust-lang.org/dist/channel-rust-1.87.0-beta.3.toml", "commit_hash": "a22ecb51f85284abc5b18a32b27696b0e3e9cf85", "rust_version": "1.87.0-beta.3"}, {"timestamp": "2025-04-12 19:20:23", "name": "channel-rust-1.87.0-beta.4.toml", "url": "https://static.rust-lang.org/dist/channel-rust-1.87.0-beta.4.toml", "commit_hash": "a5948295b4bf4c6199457f1227e5d8f6e6b9f948", "rust_version": "1.87.0-beta.4"}, {"timestamp": "2025-04-19 19:19:51", "name": "channel-rust-1.87.0-beta.5.toml", "url": "https://static.rust-lang.org/dist/channel-rust-1.87.0-beta.5.toml", "commit_hash": "386abeb93ab8e683357f54ffe76ae53861b2d984", "rust_version": "1.87.0-beta.5"}, {"timestamp": "2025-04-26 19:23:27", "name": "channel-rust-1.87.0-beta.6.toml", "url": "https://static.rust-lang.org/dist/channel-rust-1.87.0-beta.6.toml", "commit_hash": "74f40c495e867ec6b6b355b548436c7b6c967859", "rust_version": "1.87.0-beta.6"}, {"timestamp": "2025-04-29 19:20:31", "name": "channel-rust-1.87.0-beta.7.toml", "url": "https://static.rust-lang.org/dist/channel-rust-1.87.0-beta.7.toml", "commit_hash": "9d6fe3d1b2e24fad0574ef47915df47c72ba2ee3", "rust_version": "1.87.0-beta.7"}, {"timestamp": "2025-05-03 19:19:54", "name": "channel-rust-1.87.0-beta.8.toml", "url": "https://static.rust-lang.org/dist/channel-rust-1.87.0-beta.8.toml", "commit_hash": "973ec11f61ba77123aafbb2799dd24f291250a2b", "rust_version": "1.87.0-beta.8"}, {"timestamp": "2025-05-07 19:19:44", "name": "channel-rust-1.87.0-beta.9.toml", "url": "https://static.rust-lang.org/dist/channel-rust-1.87.0-beta.9.toml", "commit_hash": "af91af44eb85ceac634afa72cc73be4af358b350", "rust_version": "1.87.0-beta.9"}, {"timestamp": "2025-05-07 19:19:44", "name": "channel-rust-1.87.0-beta.toml", "url": "https://static.rust-lang.org/dist/channel-rust-1.87.0-beta.toml", "commit_hash": "af91af44eb85ceac634afa72cc73be4af358b350", "rust_version": "1.87.0-beta"}, {"timestamp": "2025-05-15 10:24:56", "name": "channel-rust-1.87.0.toml", "url": "https://static.rust-lang.org/dist/channel-rust-1.87.0.toml", "commit_hash": "17067e9ac6d7ecb70e50f92c1944e545188d2359", "rust_version": "1.87.0"}, {"timestamp": "2025-05-15 10:24:56", "name": "channel-rust-1.87.toml", "url": "https://static.rust-lang.org/dist/channel-rust-1.87.toml", "commit_hash": "17067e9ac6d7ecb70e50f92c1944e545188d2359", "rust_version": "1.87"}, {"timestamp": "2025-06-21 19:21:27", "name": "channel-rust-1.88-beta.toml", "url": "https://static.rust-lang.org/dist/channel-rust-1.88-beta.toml", "commit_hash": "32084cfdf602196490b40bb7c95ca9291c42d0cb", "rust_version": "1.88-beta"}, {"timestamp": "2025-05-09 15:52:57", "name": "channel-rust-1.88.0-beta.1.toml", "url": "https://static.rust-lang.org/dist/channel-rust-1.88.0-beta.1.toml", "commit_hash": "be8721b77bafe41f05bd77cda681a1610f44d7cd", "rust_version": "1.88.0-beta.1"}, {"timestamp": "2025-05-11 19:19:02", "name": "channel-rust-1.88.0-beta.3.toml", "url": "https://static.rust-lang.org/dist/channel-rust-1.88.0-beta.3.toml", "commit_hash": "5dadfd5c417f0b66816cb7ca662859e2c8751fb3", "rust_version": "1.88.0-beta.3"}, {"timestamp": "2025-05-25 19:24:28", "name": "channel-rust-1.88.0-beta.4.toml", "url": "https://static.rust-lang.org/dist/channel-rust-1.88.0-beta.4.toml", "commit_hash": "95597e848d27a82b8864c677ab807e9f0be1f68c", "rust_version": "1.88.0-beta.4"}, {"timestamp": "2025-06-02 19:21:51", "name": "channel-rust-1.88.0-beta.5.toml", "url": "https://static.rust-lang.org/dist/channel-rust-1.88.0-beta.5.toml", "commit_hash": "645b44edd3717f02838d07ba9bdd2554b0cdc0c5", "rust_version": "1.88.0-beta.5"}, {"timestamp": "2025-06-13 19:20:58", "name": "channel-rust-1.88.0-beta.6.toml", "url": "https://static.rust-lang.org/dist/channel-rust-1.88.0-beta.6.toml", "commit_hash": "f5534dad0efb77ca3d0c48811ba21a6f6a19f2ab", "rust_version": "1.88.0-beta.6"}, {"timestamp": "2025-06-21 19:21:27", "name": "channel-rust-1.88.0-beta.7.toml", "url": "https://static.rust-lang.org/dist/channel-rust-1.88.0-beta.7.toml", "commit_hash": "32084cfdf602196490b40bb7c95ca9291c42d0cb", "rust_version": "1.88.0-beta.7"}, {"timestamp": "2025-06-21 19:21:27", "name": "channel-rust-1.88.0-beta.toml", "url": "https://static.rust-lang.org/dist/channel-rust-1.88.0-beta.toml", "commit_hash": "32084cfdf602196490b40bb7c95ca9291c42d0cb", "rust_version": "1.88.0-beta"}, {"timestamp": "2025-06-26 11:06:24", "name": "channel-rust-1.88.0.toml", "url": "https://static.rust-lang.org/dist/channel-rust-1.88.0.toml", "commit_hash": "6b00bc3880198600130e1cf62b8f8a93494488cc", "rust_version": "1.88.0"}, {"timestamp": "2025-06-26 11:06:24", "name": "channel-rust-1.88.toml", "url": "https://static.rust-lang.org/dist/channel-rust-1.88.toml", "commit_hash": "6b00bc3880198600130e1cf62b8f8a93494488cc", "rust_version": "1.88"}, {"timestamp": "2025-08-02 19:27:09", "name": "channel-rust-1.89-beta.toml", "url": "https://static.rust-lang.org/dist/channel-rust-1.89-beta.toml", "commit_hash": "4a18378b4d4f4554cb9ca940b9b145d73aea4b85", "rust_version": "1.89-beta"}, {"timestamp": "2025-06-24 00:48:18", "name": "channel-rust-1.89.0-beta.1.toml", "url": "https://static.rust-lang.org/dist/channel-rust-1.89.0-beta.1.toml", "commit_hash": "390a0ab5dc4a895235a551e502c3893c3337731d", "rust_version": "1.89.0-beta.1"}, {"timestamp": "2025-06-25 19:33:19", "name": "channel-rust-1.89.0-beta.2.toml", "url": "https://static.rust-lang.org/dist/channel-rust-1.89.0-beta.2.toml", "commit_hash": "a8d097a4ed17700a4aaa3548dacdbca30c034277", "rust_version": "1.89.0-beta.2"}, {"timestamp": "2025-07-02 19:30:25", "name": "channel-rust-1.89.0-beta.3.toml", "url": "https://static.rust-lang.org/dist/channel-rust-1.89.0-beta.3.toml", "commit_hash": "b5e10d8c000a153cae6a14d70372dc4b39439a3f", "rust_version": "1.89.0-beta.3"}, {"timestamp": "2025-07-11 12:39:55", "name": "channel-rust-1.89.0-beta.4.toml", "url": "https://static.rust-lang.org/dist/channel-rust-1.89.0-beta.4.toml", "commit_hash": "b1237106c5e2d06b3874865bef6fc79181de32bf", "rust_version": "1.89.0-beta.4"}, {"timestamp": "2025-07-12 19:25:10", "name": "channel-rust-1.89.0-beta.5.toml", "url": "https://static.rust-lang.org/dist/channel-rust-1.89.0-beta.5.toml", "commit_hash": "c24557234c6531af7d1cfcc8f518ec4aad55d823", "rust_version": "1.89.0-beta.5"}, {"timestamp": "2025-07-21 19:27:23", "name": "channel-rust-1.89.0-beta.6.toml", "url": "https://static.rust-lang.org/dist/channel-rust-1.89.0-beta.6.toml", "commit_hash": "20c571f4ca4689572df8c27fdde8eaa36d77a11d", "rust_version": "1.89.0-beta.6"}, {"timestamp": "2025-07-25 19:27:15", "name": "channel-rust-1.89.0-beta.7.toml", "url": "https://static.rust-lang.org/dist/channel-rust-1.89.0-beta.7.toml", "commit_hash": "4229c2e708ce796c71747b7fa177ff4ef9aa794c", "rust_version": "1.89.0-beta.7"}, {"timestamp": "2025-08-02 19:27:10", "name": "channel-rust-1.89.0-beta.8.toml", "url": "https://static.rust-lang.org/dist/channel-rust-1.89.0-beta.8.toml", "commit_hash": "4a18378b4d4f4554cb9ca940b9b145d73aea4b85", "rust_version": "1.89.0-beta.8"}, {"timestamp": "2025-08-02 19:27:10", "name": "channel-rust-1.89.0-beta.toml", "url": "https://static.rust-lang.org/dist/channel-rust-1.89.0-beta.toml", "commit_hash": "4a18378b4d4f4554cb9ca940b9b145d73aea4b85", "rust_version": "1.89.0-beta"}, {"timestamp": "2025-08-07 03:53:33", "name": "channel-rust-1.89.0.toml", "url": "https://static.rust-lang.org/dist/channel-rust-1.89.0.toml", "commit_hash": "29483883eed69d5fb4db01964cdf2af4d86e9cb2", "rust_version": "1.89.0"}, {"timestamp": "2025-08-07 03:53:33", "name": "channel-rust-1.89.toml", "url": "https://static.rust-lang.org/dist/channel-rust-1.89.toml", "commit_hash": "29483883eed69d5fb4db01964cdf2af4d86e9cb2", "rust_version": "1.89"}, {"timestamp": "2025-09-11 19:22:40", "name": "channel-rust-1.90-beta.toml", "url": "https://static.rust-lang.org/dist/channel-rust-1.90-beta.toml", "commit_hash": "67cb8e039bd8df7ca6c38828756cc22ce335724e", "rust_version": "1.90-beta"}, {"timestamp": "2025-08-04 19:27:36", "name": "channel-rust-1.90.0-beta.1.toml", "url": "https://static.rust-lang.org/dist/channel-rust-1.90.0-beta.1.toml", "commit_hash": "788da80fcfcef3f34c90def5baa32813e39a1a41", "rust_version": "1.90.0-beta.1"}, {"timestamp": "2025-09-11 19:22:40", "name": "channel-rust-1.90.0-beta.10.toml", "url": "https://static.rust-lang.org/dist/channel-rust-1.90.0-beta.10.toml", "commit_hash": "67cb8e039bd8df7ca6c38828756cc22ce335724e", "rust_version": "1.90.0-beta.10"}, {"timestamp": "2025-08-09 19:27:48", "name": "channel-rust-1.90.0-beta.2.toml", "url": "https://static.rust-lang.org/dist/channel-rust-1.90.0-beta.2.toml", "commit_hash": "96ecc9042cbda2be93f969f2b8dc676964ec8f2c", "rust_version": "1.90.0-beta.2"}, {"timestamp": "2025-08-16 19:25:25", "name": "channel-rust-1.90.0-beta.3.toml", "url": "https://static.rust-lang.org/dist/channel-rust-1.90.0-beta.3.toml", "commit_hash": "630a5f1d3cda0e54d878f3f6bf9be435ee4c68a5", "rust_version": "1.90.0-beta.3"}, {"timestamp": "2025-08-17 19:23:01", "name": "channel-rust-1.90.0-beta.4.toml", "url": "https://static.rust-lang.org/dist/channel-rust-1.90.0-beta.4.toml", "commit_hash": "47b72a3455b75c1e33aa211e516255752352681e", "rust_version": "1.90.0-beta.4"}, {"timestamp": "2025-08-19 19:23:09", "name": "channel-rust-1.90.0-beta.5.toml", "url": "https://static.rust-lang.org/dist/channel-rust-1.90.0-beta.5.toml", "commit_hash": "49fc0cc3e9ae608b4938b2c7640fc6106446a9b6", "rust_version": "1.90.0-beta.5"}, {"timestamp": "2025-08-21 19:22:55", "name": "channel-rust-1.90.0-beta.6.toml", "url": "https://static.rust-lang.org/dist/channel-rust-1.90.0-beta.6.toml", "commit_hash": "085bdc2aee2772c4f392a8afcd5421a8e8b6e9e4", "rust_version": "1.90.0-beta.6"}, {"timestamp": "2025-08-29 19:22:17", "name": "channel-rust-1.90.0-beta.7.toml", "url": "https://static.rust-lang.org/dist/channel-rust-1.90.0-beta.7.toml", "commit_hash": "fb918cec013920472f6975b2009b0339d9e8cc9c", "rust_version": "1.90.0-beta.7"}, {"timestamp": "2025-09-10 19:24:58", "name": "channel-rust-1.90.0-beta.8.toml", "url": "https://static.rust-lang.org/dist/channel-rust-1.90.0-beta.8.toml", "commit_hash": "1c785abde778e1173dce1aba1ae471814c8fa1ab", "rust_version": "1.90.0-beta.8"}, {"timestamp": "2025-09-11 19:22:40", "name": "channel-rust-1.90.0-beta.toml", "url": "https://static.rust-lang.org/dist/channel-rust-1.90.0-beta.toml", "commit_hash": "67cb8e039bd8df7ca6c38828756cc22ce335724e", "rust_version": "1.90.0-beta"}, {"timestamp": "2025-09-18 06:29:58", "name": "channel-rust-1.90.0.toml", "url": "https://static.rust-lang.org/dist/channel-rust-1.90.0.toml", "commit_hash": "1159e78c4747b02ef996e55082b704c09b970588", "rust_version": "1.90.0"}, {"timestamp": "2025-09-18 06:29:58", "name": "channel-rust-1.90.toml", "url": "https://static.rust-lang.org/dist/channel-rust-1.90.toml", "commit_hash": "1159e78c4747b02ef996e55082b704c09b970588", "rust_version": "1.90"}, {"timestamp": "2025-10-25 19:41:55", "name": "channel-rust-1.91-beta.toml", "url": "https://static.rust-lang.org/dist/channel-rust-1.91-beta.toml", "commit_hash": "f2f881bb99cf03bca0c54b4a0b1209b40b8cc383", "rust_version": "1.91-beta"}, {"timestamp": "2025-09-15 19:34:02", "name": "channel-rust-1.91.0-beta.1.toml", "url": "https://static.rust-lang.org/dist/channel-rust-1.91.0-beta.1.toml", "commit_hash": "1bffa230015ba3c7826f6c5aceb0dc6e940d357e", "rust_version": "1.91.0-beta.1"}, {"timestamp": "2025-10-25 19:41:55", "name": "channel-rust-1.91.0-beta.10.toml", "url": "https://static.rust-lang.org/dist/channel-rust-1.91.0-beta.10.toml", "commit_hash": "f2f881bb99cf03bca0c54b4a0b1209b40b8cc383", "rust_version": "1.91.0-beta.10"}, {"timestamp": "2025-09-19 19:35:37", "name": "channel-rust-1.91.0-beta.2.toml", "url": "https://static.rust-lang.org/dist/channel-rust-1.91.0-beta.2.toml", "commit_hash": "b34cfaf51ab461e8aeb742c40ca790a4e5feefe1", "rust_version": "1.91.0-beta.2"}, {"timestamp": "2025-09-20 19:32:09", "name": "channel-rust-1.91.0-beta.3.toml", "url": "https://static.rust-lang.org/dist/channel-rust-1.91.0-beta.3.toml", "commit_hash": "bb624dcb4c8ab987e10c0808d92d76f3b84dd117", "rust_version": "1.91.0-beta.3"}, {"timestamp": "2025-09-27 19:31:57", "name": "channel-rust-1.91.0-beta.4.toml", "url": "https://static.rust-lang.org/dist/channel-rust-1.91.0-beta.4.toml", "commit_hash": "aa7859c0dec2de6c9cab34b03028bcef7b1fc25d", "rust_version": "1.91.0-beta.4"}, {"timestamp": "2025-10-08 19:36:42", "name": "channel-rust-1.91.0-beta.5.toml", "url": "https://static.rust-lang.org/dist/channel-rust-1.91.0-beta.5.toml", "commit_hash": "21cd82aa6363f7ceaebefafc528e62124267461c", "rust_version": "1.91.0-beta.5"}, {"timestamp": "2025-10-12 19:38:44", "name": "channel-rust-1.91.0-beta.6.toml", "url": "https://static.rust-lang.org/dist/channel-rust-1.91.0-beta.6.toml", "commit_hash": "cbf84ed0ca316895a576e163bb34c0cdf7d2a0f6", "rust_version": "1.91.0-beta.6"}, {"timestamp": "2025-10-14 19:36:43", "name": "channel-rust-1.91.0-beta.7.toml", "url": "https://static.rust-lang.org/dist/channel-rust-1.91.0-beta.7.toml", "commit_hash": "d69b1bb497589b25ca3925f9290420f29c6f44d5", "rust_version": "1.91.0-beta.7"}, {"timestamp": "2025-10-15 19:38:43", "name": "channel-rust-1.91.0-beta.8.toml", "url": "https://static.rust-lang.org/dist/channel-rust-1.91.0-beta.8.toml", "commit_hash": "df8b2e497d915c0201c532aa8791892b5ae6a78d", "rust_version": "1.91.0-beta.8"}, {"timestamp": "2025-10-17 19:36:53", "name": "channel-rust-1.91.0-beta.9.toml", "url": "https://static.rust-lang.org/dist/channel-rust-1.91.0-beta.9.toml", "commit_hash": "1f251978870710eb72e96cb586ab8cb42fa90c6a", "rust_version": "1.91.0-beta.9"}, {"timestamp": "2025-10-25 19:41:55", "name": "channel-rust-1.91.0-beta.toml", "url": "https://static.rust-lang.org/dist/channel-rust-1.91.0-beta.toml", "commit_hash": "f2f881bb99cf03bca0c54b4a0b1209b40b8cc383", "rust_version": "1.91.0-beta"}, {"timestamp": "2025-10-30 11:28:06", "name": "channel-rust-1.91.0.toml", "url": "https://static.rust-lang.org/dist/channel-rust-1.91.0.toml", "commit_hash": "f8297e351a40c1439a467bbbb6879088047f50b3", "rust_version": "1.91.0"}, {"timestamp": "2025-11-10 11:00:37", "name": "channel-rust-1.91.1.toml", "url": "https://static.rust-lang.org/dist/channel-rust-1.91.1.toml", "commit_hash": "ed61e7d7e242494fb7057f2657300d9e77bb4fcb", "rust_version": "1.91.1"}, {"timestamp": "2025-11-10 11:00:37", "name": "channel-rust-1.91.toml", "url": "https://static.rust-lang.org/dist/channel-rust-1.91.toml", "commit_hash": "ed61e7d7e242494fb7057f2657300d9e77bb4fcb", "rust_version": "1.91"}, {"timestamp": "2025-11-09 18:47:26", "name": "channel-rust-1.92-beta.toml", "url": "https://static.rust-lang.org/dist/channel-rust-1.92-beta.toml", "commit_hash": "f3f12444a017add0468f683f3a10656d29438a05", "rust_version": "1.92-beta"}, {"timestamp": "2025-10-28 12:35:11", "name": "channel-rust-1.92.0-beta.1.toml", "url": "https://static.rust-lang.org/dist/channel-rust-1.92.0-beta.1.toml", "commit_hash": "3b4dd9bf1410f8da6329baa36ce5e37673cbbd1f", "rust_version": "1.92.0-beta.1"}, {"timestamp": "2025-10-31 19:47:49", "name": "channel-rust-1.92.0-beta.2.toml", "url": "https://static.rust-lang.org/dist/channel-rust-1.92.0-beta.2.toml", "commit_hash": "0a411606e9cc00588c83fcddc924395fe41079ac", "rust_version": "1.92.0-beta.2"}, {"timestamp": "2025-11-09 18:47:26", "name": "channel-rust-1.92.0-beta.3.toml", "url": "https://static.rust-lang.org/dist/channel-rust-1.92.0-beta.3.toml", "commit_hash": "f3f12444a017add0468f683f3a10656d29438a05", "rust_version": "1.92.0-beta.3"}, {"timestamp": "2025-11-09 18:47:26", "name": "channel-rust-1.92.0-beta.toml", "url": "https://static.rust-lang.org/dist/channel-rust-1.92.0-beta.toml", "commit_hash": "f3f12444a017add0468f683f3a10656d29438a05", "rust_version": "1.92.0-beta"}, {"timestamp": "2025-11-09 18:47:26", "name": "channel-rust-beta.toml", "url": "https://static.rust-lang.org/dist/channel-rust-beta.toml", "commit_hash": "f3f12444a017add0468f683f3a10656d29438a05", "rust_version": "beta"}, {"timestamp": "2025-11-13 17:37:26", "name": "channel-rust-nightly.toml", "url": "https://static.rust-lang.org/dist/channel-rust-nightly.toml", "commit_hash": "2286e5d224b3413484cf4f398a9f078487e7b49d", "rust_version": "nightly"}, {"timestamp": "2025-11-10 11:00:37", "name": "channel-rust-stable.toml", "url": "https://static.rust-lang.org/dist/channel-rust-stable.toml", "commit_hash": "ed61e7d7e242494fb7057f2657300d9e77bb4fcb", "rust_version": "stable"}]}